rdkit_heatmaps/__init__.py
rdkit_heatmaps/functions.py
rdkit_heatmaps/heatmaps.py
rdkit_heatmaps/molmapping.py
rdkit_heatmaps/utils.py
rdkit_heatmaps-0.1.dist-info/METADATA
rdkit_heatmaps-0.1.dist-info/WHEEL
rdkit_heatmaps-0.1.dist-info/top_level.txt
rdkit_heatmaps-0.1.dist-info/RECORD
