Metadata-Version: 2.4
Name: rdkit_heatmaps
Version: 0.1
Summary: Toolkit for more custom heatmaps in RDKit
Author: Christian Feldmann
Author-email: cfeldmann@bit.uni-bonn.de
License: BSD
Requires-Dist: numpy
Requires-Dist: matplotlib
Requires-Dist: pillow
Dynamic: author
Dynamic: author-email
Dynamic: license
Dynamic: requires-dist
Dynamic: summary
